{"date":"20260713","results":[{"race_id":"202607132401","venue":"宇都宮","race_no":1,"finishers":[{"rank":1,"waku":5,"umaban":5,"name":"松田安綱","kimarite":"逃"},{"rank":2,"waku":3,"umaban":3,"name":"山田雅之","kimarite":"ク"},{"rank":3,"waku":6,"umaban":7,"name":"田頭寛之","kimarite":""},{"rank":4,"waku":2,"umaban":2,"name":"川崎健次","kimarite":""},{"rank":5,"waku":4,"umaban":4,"name":"梅原大治","kimarite":""}],"paybacks":[{"type":"2車単","combination":"5-3","payout":370},{"type":"2車複","combination":"3-5","payout":300},{"type":"ワイド","combination":"3-5","payout":140},{"type":"ワイド","combination":"3-7","payout":260},{"type":"ワイド","combination":"5-7","payout":150},{"type":"3連単","combination":"5-3-7","payout":1690},{"type":"3連複","combination":"3-5-7","payout":490}]},{"race_id":"202607132402","venue":"宇都宮","race_no":2,"finishers":[{"rank":1,"waku":2,"umaban":2,"name":"岡本英之","kimarite":"差"},{"rank":2,"waku":6,"umaban":7,"name":"鈴木小次廊","kimarite":"捲"},{"rank":3,"waku":5,"umaban":5,"name":"河上陽一","kimarite":""},{"rank":4,"waku":1,"umaban":1,"name":"吉永好宏","kimarite":""},{"rank":5,"waku":3,"umaban":3,"name":"松岡晋乃介","kimarite":""}],"paybacks":[{"type":"2車単","combination":"2-7","payout":380},{"type":"2車複","combination":"2-7","payout":270},{"type":"ワイド","combination":"2-5","payout":270},{"type":"ワイド","combination":"2-7","payout":160},{"type":"ワイド","combination":"5-7","payout":500},{"type":"3連単","combination":"2-7-5","payout":1450},{"type":"3連複","combination":"2-5-7","payout":750}]},{"race_id":"202607132403","venue":"宇都宮","race_no":3,"finishers":[{"rank":1,"waku":5,"umaban":5,"name":"田中会心","kimarite":"逃"},{"rank":2,"waku":1,"umaban":1,"name":"吉川希望","kimarite":"差"},{"rank":3,"waku":2,"umaban":2,"name":"梶原恵介","kimarite":""},{"rank":4,"waku":4,"umaban":4,"name":"宮司周郎","kimarite":""},{"rank":5,"waku":3,"umaban":3,"name":"本田拓也","kimarite":""}],"paybacks":[{"type":"2車単","combination":"5-1","payout":1480},{"type":"2車複","combination":"1-5","payout":460},{"type":"ワイド","combination":"1-2","payout":270},{"type":"ワイド","combination":"1-5","payout":240},{"type":"ワイド","combination":"2-5","payout":310},{"type":"3連単","combination":"5-1-2","payout":3550},{"type":"3連複","combination":"1-2-5","payout":550}]},{"race_id":"202607132404","venue":"宇都宮","race_no":4,"finishers":[{"rank":1,"waku":1,"umaban":1,"name":"内山慧大","kimarite":"捲"},{"rank":2,"waku":6,"umaban":7,"name":"坂本将太郎","kimarite":"ク"},{"rank":3,"waku":4,"umaban":4,"name":"佐藤謙","kimarite":""},{"rank":4,"waku":5,"umaban":5,"name":"山本康旗","kimarite":""},{"rank":5,"waku":2,"umaban":2,"name":"須永勝太","kimarite":""}],"paybacks":[{"type":"2車単","combination":"1-7","payout":230},{"type":"2車複","combination":"1-7","payout":170},{"type":"ワイド","combination":"1-4","payout":200},{"type":"ワイド","combination":"1-7","payout":120},{"type":"ワイド","combination":"4-7","payout":210},{"type":"3連単","combination":"1-7-4","payout":410},{"type":"3連複","combination":"1-4-7","payout":200}]},{"race_id":"202607132405","venue":"宇都宮","race_no":5,"finishers":[{"rank":1,"waku":4,"umaban":4,"name":"白上翔","kimarite":"差"},{"rank":2,"waku":2,"umaban":2,"name":"吉田智哉","kimarite":"差"},{"rank":3,"waku":1,"umaban":1,"name":"藤原憲征","kimarite":""},{"rank":4,"waku":6,"umaban":7,"name":"橋本智昭","kimarite":""},{"rank":5,"waku":6,"umaban":6,"name":"久樹克門","kimarite":""}],"paybacks":[{"type":"2車単","combination":"4-2","payout":4620},{"type":"2車複","combination":"2-4","payout":3010},{"type":"ワイド","combination":"1-2","payout":1880},{"type":"ワイド","combination":"1-4","payout":470},{"type":"ワイド","combination":"2-4","payout":1420},{"type":"3連単","combination":"4-2-1","payout":32540},{"type":"3連複","combination":"1-2-4","payout":5280}]},{"race_id":"202607132406","venue":"宇都宮","race_no":6,"finishers":[{"rank":1,"waku":2,"umaban":2,"name":"青木瑞樹","kimarite":"逃"},{"rank":2,"waku":6,"umaban":7,"name":"山本奨","kimarite":"ク"},{"rank":3,"waku":1,"umaban":1,"name":"佐藤博紀","kimarite":""},{"rank":4,"waku":5,"umaban":5,"name":"瀬戸晋作","kimarite":""},{"rank":5,"waku":3,"umaban":3,"name":"高木和仁","kimarite":""}],"paybacks":[{"type":"2車単","combination":"2-7","payout":590},{"type":"2車複","combination":"2-7","payout":240},{"type":"ワイド","combination":"1-2","payout":200},{"type":"ワイド","combination":"1-7","payout":170},{"type":"ワイド","combination":"2-7","payout":170},{"type":"3連単","combination":"2-7-1","payout":2440},{"type":"3連複","combination":"1-2-7","payout":370}]},{"race_id":"202607132407","venue":"宇都宮","race_no":7,"finishers":[{"rank":1,"waku":2,"umaban":2,"name":"和泉尚吾","kimarite":"捲"},{"rank":2,"waku":3,"umaban":3,"name":"伊藤正樹","kimarite":"差"},{"rank":3,"waku":6,"umaban":7,"name":"掛水泰範","kimarite":""},{"rank":4,"waku":5,"umaban":5,"name":"稲毛知也","kimarite":""},{"rank":5,"waku":1,"umaban":1,"name":"城幸弘","kimarite":""}],"paybacks":[{"type":"2車単","combination":"2-3","payout":2370},{"type":"2車複","combination":"2-3","payout":1050},{"type":"ワイド","combination":"2-3","payout":230},{"type":"ワイド","combination":"2-7","payout":150},{"type":"ワイド","combination":"3-7","payout":290},{"type":"3連単","combination":"2-3-7","payout":5460},{"type":"3連複","combination":"2-3-7","payout":560}]},{"race_id":"202607132408","venue":"宇都宮","race_no":8,"finishers":[{"rank":1,"waku":6,"umaban":7,"name":"椎木尾拓哉","kimarite":"差"},{"rank":2,"waku":3,"umaban":3,"name":"小柳智徳","kimarite":"逃"},{"rank":3,"waku":1,"umaban":1,"name":"清水剛志","kimarite":""},{"rank":4,"waku":6,"umaban":6,"name":"谷津田将吾","kimarite":""},{"rank":5,"waku":2,"umaban":2,"name":"内藤高裕","kimarite":""}],"paybacks":[{"type":"2車単","combination":"7-3","payout":5010},{"type":"2車複","combination":"3-7","payout":1900},{"type":"ワイド","combination":"1-3","payout":420},{"type":"ワイド","combination":"1-7","payout":320},{"type":"ワイド","combination":"3-7","payout":830},{"type":"3連単","combination":"7-3-1","payout":14240},{"type":"3連複","combination":"1-3-7","payout":1800}]},{"race_id":"202607132409","venue":"宇都宮","race_no":9,"finishers":[{"rank":1,"waku":2,"umaban":2,"name":"柿澤大貴","kimarite":"差"},{"rank":2,"waku":4,"umaban":4,"name":"加藤将武","kimarite":"捲"},{"rank":3,"waku":5,"umaban":5,"name":"佐川翔吾","kimarite":""},{"rank":4,"waku":1,"umaban":1,"name":"西田雅志","kimarite":""},{"rank":5,"waku":6,"umaban":6,"name":"山根慶太","kimarite":""}],"paybacks":[{"type":"2車単","combination":"2-4","payout":320},{"type":"2車複","combination":"2-4","payout":310},{"type":"ワイド","combination":"2-4","payout":140},{"type":"ワイド","combination":"2-5","payout":220},{"type":"ワイド","combination":"4-5","payout":450},{"type":"3連単","combination":"2-4-5","payout":1160},{"type":"3連複","combination":"2-4-5","payout":540}]},{"race_id":"202607132410","venue":"宇都宮","race_no":10,"finishers":[{"rank":1,"waku":2,"umaban":2,"name":"小堺浩二","kimarite":"差"},{"rank":2,"waku":5,"umaban":5,"name":"阿部英斗","kimarite":"捲"},{"rank":3,"waku":3,"umaban":3,"name":"中村浩士","kimarite":""},{"rank":4,"waku":6,"umaban":6,"name":"花田将司","kimarite":""},{"rank":5,"waku":6,"umaban":7,"name":"松岡篤哉","kimarite":""}],"paybacks":[{"type":"2車単","combination":"2-5","payout":3400},{"type":"2車複","combination":"2-5","payout":550},{"type":"ワイド","combination":"2-3","payout":1250},{"type":"ワイド","combination":"2-5","payout":260},{"type":"ワイド","combination":"3-5","payout":410},{"type":"3連単","combination":"2-5-3","payout":25300},{"type":"3連複","combination":"2-3-5","payout":2260}]},{"race_id":"202607132411","venue":"宇都宮","race_no":11,"finishers":[{"rank":1,"waku":4,"umaban":4,"name":"中川貴徳","kimarite":"差"},{"rank":2,"waku":1,"umaban":1,"name":"長田龍拳","kimarite":"逃"},{"rank":3,"waku":6,"umaban":6,"name":"吉田裕全","kimarite":""},{"rank":4,"waku":2,"umaban":2,"name":"吉武信太朗","kimarite":""},{"rank":5,"waku":6,"umaban":7,"name":"近藤誠二","kimarite":""}],"paybacks":[{"type":"2車単","combination":"4-1","payout":300},{"type":"2車複","combination":"1-4","payout":100},{"type":"ワイド","combination":"1-4","payout":100},{"type":"ワイド","combination":"1-6","payout":220},{"type":"ワイド","combination":"4-6","payout":210},{"type":"3連単","combination":"4-1-6","payout":590},{"type":"3連複","combination":"1-4-6","payout":210}]},{"race_id":"202607132412","venue":"宇都宮","race_no":12,"finishers":[{"rank":1,"waku":6,"umaban":7,"name":"佐々木眞也","kimarite":"差"},{"rank":2,"waku":5,"umaban":5,"name":"南潤","kimarite":"逃"},{"rank":3,"waku":2,"umaban":2,"name":"伊藤旭","kimarite":""},{"rank":4,"waku":3,"umaban":3,"name":"嵯峨昇喜郎","kimarite":""},{"rank":5,"waku":4,"umaban":4,"name":"山口富生","kimarite":""}],"paybacks":[{"type":"2車単","combination":"7-5","payout":4400},{"type":"2車複","combination":"5-7","payout":2260},{"type":"ワイド","combination":"2-5","payout":1220},{"type":"ワイド","combination":"2-7","payout":320},{"type":"ワイド","combination":"5-7","payout":1040},{"type":"3連単","combination":"7-5-2","payout":20840},{"type":"3連複","combination":"2-5-7","payout":4120}]},{"race_id":"202607132701","venue":"京王閣","race_no":1,"finishers":[{"rank":1,"waku":4,"umaban":4,"name":"片岡遼真","kimarite":"逃"},{"rank":2,"waku":3,"umaban":3,"name":"小川辰徳","kimarite":"逃"},{"rank":3,"waku":2,"umaban":2,"name":"天沼雅貴","kimarite":""},{"rank":4,"waku":6,"umaban":7,"name":"関戸努","kimarite":""},{"rank":5,"waku":1,"umaban":1,"name":"窪田陽介","kimarite":""}],"paybacks":[{"type":"2車単","combination":"4-3","payout":3220},{"type":"2車複","combination":"3-4","payout":2630},{"type":"ワイド","combination":"2-3","payout":590},{"type":"ワイド","combination":"2-4","payout":700},{"type":"ワイド","combination":"3-4","payout":720},{"type":"3連単","combination":"4-3-2","payout":7880},{"type":"3連複","combination":"2-3-4","payout":1980}]},{"race_id":"202607132702","venue":"京王閣","race_no":2,"finishers":[{"rank":1,"waku":6,"umaban":7,"name":"篠原輝利","kimarite":"逃"},{"rank":2,"waku":1,"umaban":1,"name":"本間慎吾","kimarite":"ク"},{"rank":3,"waku":4,"umaban":4,"name":"安坂洋一","kimarite":""},{"rank":4,"waku":5,"umaban":5,"name":"畠山裕行","kimarite":""},{"rank":5,"waku":2,"umaban":2,"name":"森川康輔","kimarite":""}],"paybacks":[{"type":"2車単","combination":"7-1","payout":230},{"type":"2車複","combination":"1-7","payout":180},{"type":"ワイド","combination":"1-4","payout":640},{"type":"ワイド","combination":"1-7","payout":150},{"type":"ワイド","combination":"4-7","payout":400},{"type":"3連単","combination":"7-1-4","payout":1520},{"type":"3連複","combination":"1-4-7","payout":1180}]},{"race_id":"202607134301","venue":"岐阜","race_no":1,"finishers":[{"rank":1,"waku":3,"umaban":3,"name":"山田哲也","kimarite":"差"},{"rank":2,"waku":6,"umaban":7,"name":"井田晶之","kimarite":"差"},{"rank":3,"waku":5,"umaban":5,"name":"坂本毅","kimarite":""},{"rank":4,"waku":6,"umaban":6,"name":"石井毅","kimarite":""},{"rank":5,"waku":1,"umaban":1,"name":"堀政美","kimarite":""}],"paybacks":[{"type":"2車単","combination":"3-7","payout":1610},{"type":"2車複","combination":"3-7","payout":440},{"type":"ワイド","combination":"3-5","payout":1350},{"type":"ワイド","combination":"3-7","payout":220},{"type":"ワイド","combination":"5-7","payout":820},{"type":"3連単","combination":"3-7-5","payout":12130},{"type":"3連複","combination":"3-5-7","payout":2810}]},{"race_id":"202607134302","venue":"岐阜","race_no":2,"finishers":[{"rank":1,"waku":6,"umaban":7,"name":"鶴淳志","kimarite":"逃"},{"rank":2,"waku":6,"umaban":6,"name":"伊藤拓人","kimarite":"差"},{"rank":3,"waku":2,"umaban":2,"name":"小松剛之","kimarite":""},{"rank":4,"waku":4,"umaban":4,"name":"柳原司","kimarite":""},{"rank":5,"waku":3,"umaban":3,"name":"樋口瑛土","kimarite":""}],"paybacks":[{"type":"2車単","combination":"7-6","payout":5510},{"type":"2車複","combination":"6-7","payout":3620},{"type":"ワイド","combination":"2-6","payout":1240},{"type":"ワイド","combination":"2-7","payout":230},{"type":"ワイド","combination":"6-7","payout":1280},{"type":"3連単","combination":"7-6-2","payout":13550},{"type":"3連複","combination":"2-6-7","payout":2470}]},{"race_id":"202607134303","venue":"岐阜","race_no":3,"finishers":[{"rank":1,"waku":2,"umaban":2,"name":"池部壮太","kimarite":"差"},{"rank":2,"waku":3,"umaban":3,"name":"川口満宏","kimarite":"差"},{"rank":3,"waku":4,"umaban":4,"name":"小坂丈","kimarite":""},{"rank":4,"waku":6,"umaban":6,"name":"高橋清太郎","kimarite":""},{"rank":5,"waku":6,"umaban":7,"name":"田中秀治","kimarite":""}],"paybacks":[{"type":"2車単","combination":"2-3","payout":5950},{"type":"2車複","combination":"2-3","payout":4030},{"type":"ワイド","combination":"2-3","payout":1570},{"type":"ワイド","combination":"2-4","payout":2180},{"type":"ワイド","combination":"3-4","payout":580},{"type":"3連単","combination":"2-3-4","payout":34010},{"type":"3連複","combination":"2-3-4","payout":4070}]},{"race_id":"202607134304","venue":"岐阜","race_no":4,"finishers":[{"rank":1,"waku":4,"umaban":4,"name":"中釜健次","kimarite":"捲"},{"rank":2,"waku":1,"umaban":1,"name":"川木敬大","kimarite":"ク"},{"rank":3,"waku":6,"umaban":7,"name":"山崎航","kimarite":""},{"rank":4,"waku":2,"umaban":2,"name":"成田直喜","kimarite":""},{"rank":5,"waku":3,"umaban":3,"name":"舛井幹雄","kimarite":""}],"paybacks":[{"type":"2車単","combination":"4-1","payout":870},{"type":"2車複","combination":"1-4","payout":860},{"type":"ワイド","combination":"1-4","payout":360},{"type":"ワイド","combination":"1-7","payout":480},{"type":"ワイド","combination":"4-7","payout":190},{"type":"3連単","combination":"4-1-7","payout":3440},{"type":"3連複","combination":"1-4-7","payout":830}]},{"race_id":"202607134305","venue":"岐阜","race_no":5,"finishers":[{"rank":1,"waku":6,"umaban":6,"name":"小西晴己","kimarite":"差"},{"rank":2,"waku":2,"umaban":2,"name":"山本巨樹","kimarite":"差"},{"rank":3,"waku":4,"umaban":4,"name":"岩本和也","kimarite":""},{"rank":4,"waku":5,"umaban":5,"name":"渡辺正光","kimarite":""},{"rank":5,"waku":1,"umaban":1,"name":"望月湧世","kimarite":""}],"paybacks":[{"type":"2車単","combination":"6-2","payout":2260},{"type":"2車複","combination":"2-6","payout":1630},{"type":"ワイド","combination":"2-4","payout":630},{"type":"ワイド","combination":"2-6","payout":390},{"type":"ワイド","combination":"4-6","payout":210},{"type":"3連単","combination":"6-2-4","payout":5300},{"type":"3連複","combination":"2-4-6","payout":1430}]},{"race_id":"202607134306","venue":"岐阜","race_no":6,"finishers":[{"rank":1,"waku":5,"umaban":5,"name":"張野幸聖","kimarite":"捲"},{"rank":2,"waku":3,"umaban":3,"name":"関貴之","kimarite":"差"},{"rank":3,"waku":2,"umaban":2,"name":"三谷政史","kimarite":""},{"rank":4,"waku":6,"umaban":6,"name":"内田英介","kimarite":""},{"rank":5,"waku":4,"umaban":4,"name":"村上直久","kimarite":""}],"paybacks":[{"type":"2車単","combination":"5-3","payout":3060},{"type":"2車複","combination":"3-5","payout":2240},{"type":"ワイド","combination":"2-3","payout":860},{"type":"ワイド","combination":"2-5","payout":420},{"type":"ワイド","combination":"3-5","payout":790},{"type":"3連単","combination":"5-3-2","payout":9750},{"type":"3連複","combination":"2-3-5","payout":2280}]},{"race_id":"202607134307","venue":"岐阜","race_no":7,"finishers":[{"rank":1,"waku":3,"umaban":3,"name":"川上隆義","kimarite":"逃"},{"rank":2,"waku":4,"umaban":4,"name":"平原啓多","kimarite":"ク"},{"rank":3,"waku":6,"umaban":6,"name":"吉田勇人","kimarite":""},{"rank":4,"waku":5,"umaban":5,"name":"西岡正一","kimarite":""},{"rank":5,"waku":1,"umaban":1,"name":"吉川起也","kimarite":""}],"paybacks":[{"type":"2車単","combination":"3-4","payout":360},{"type":"2車複","combination":"3-4","payout":270},{"type":"ワイド","combination":"3-4","payout":220},{"type":"ワイド","combination":"3-6","payout":340},{"type":"ワイド","combination":"4-6","payout":330},{"type":"3連単","combination":"3-4-6","payout":590},{"type":"3連複","combination":"3-4-6","payout":390}]},{"race_id":"202607134308","venue":"岐阜","race_no":8,"finishers":[{"rank":1,"waku":6,"umaban":7,"name":"筒井敦史","kimarite":"差"},{"rank":2,"waku":1,"umaban":1,"name":"高田修汰","kimarite":"逃"},{"rank":3,"waku":5,"umaban":5,"name":"森川大輔","kimarite":""},{"rank":4,"waku":4,"umaban":4,"name":"柴崎俊光","kimarite":""},{"rank":5,"waku":2,"umaban":2,"name":"兼本将太","kimarite":""}],"paybacks":[{"type":"2車単","combination":"7-1","payout":9560},{"type":"2車複","combination":"1-7","payout":4660},{"type":"ワイド","combination":"1-5","payout":360},{"type":"ワイド","combination":"1-7","payout":960},{"type":"ワイド","combination":"5-7","payout":220},{"type":"3連単","combination":"7-1-5","payout":28110},{"type":"3連複","combination":"1-5-7","payout":1930}]},{"race_id":"202607134309","venue":"岐阜","race_no":9,"finishers":[{"rank":1,"waku":4,"umaban":4,"name":"新村穣","kimarite":"差"},{"rank":2,"waku":2,"umaban":2,"name":"岡本総","kimarite":"捲"},{"rank":3,"waku":6,"umaban":7,"name":"坂本修一","kimarite":""},{"rank":4,"waku":1,"umaban":1,"name":"萩原孝之","kimarite":""},{"rank":5,"waku":6,"umaban":6,"name":"三ツ石康洋","kimarite":""}],"paybacks":[{"type":"2車単","combination":"4-2","payout":4910},{"type":"2車複","combination":"2-4","payout":1790},{"type":"ワイド","combination":"2-4","payout":640},{"type":"ワイド","combination":"2-7","payout":320},{"type":"ワイド","combination":"4-7","payout":630},{"type":"3連単","combination":"4-2-7","payout":23930},{"type":"3連複","combination":"2-4-7","payout":2850}]},{"race_id":"202607134310","venue":"岐阜","race_no":10,"finishers":[{"rank":1,"waku":4,"umaban":4,"name":"竹内智彦","kimarite":"差"},{"rank":2,"waku":2,"umaban":2,"name":"武田亮","kimarite":"逃"},{"rank":3,"waku":6,"umaban":7,"name":"荻原尚人","kimarite":""},{"rank":4,"waku":1,"umaban":1,"name":"福島武士","kimarite":""},{"rank":5,"waku":3,"umaban":3,"name":"久保田泰弘","kimarite":""}],"paybacks":[{"type":"2車単","combination":"4-2","payout":540},{"type":"2車複","combination":"2-4","payout":340},{"type":"ワイド","combination":"2-4","payout":200},{"type":"ワイド","combination":"2-7","payout":640},{"type":"ワイド","combination":"4-7","payout":400},{"type":"3連単","combination":"4-2-7","payout":1190},{"type":"3連複","combination":"2-4-7","payout":580}]},{"race_id":"202607134311","venue":"岐阜","race_no":11,"finishers":[{"rank":1,"waku":3,"umaban":3,"name":"仁藤秀","kimarite":"差"},{"rank":2,"waku":4,"umaban":4,"name":"藤田祐大","kimarite":"捲"},{"rank":3,"waku":2,"umaban":2,"name":"金澤竜二","kimarite":""},{"rank":4,"waku":5,"umaban":5,"name":"宇佐見優介","kimarite":""},{"rank":5,"waku":6,"umaban":7,"name":"岩本純","kimarite":""}],"paybacks":[{"type":"2車単","combination":"3-4","payout":380},{"type":"2車複","combination":"3-4","payout":230},{"type":"ワイド","combination":"2-3","payout":200},{"type":"ワイド","combination":"2-4","payout":390},{"type":"ワイド","combination":"3-4","payout":160},{"type":"3連単","combination":"3-4-2","payout":1300},{"type":"3連複","combination":"2-3-4","payout":510}]},{"race_id":"202607134312","venue":"岐阜","race_no":12,"finishers":[{"rank":1,"waku":1,"umaban":1,"name":"志田龍星","kimarite":"捲"},{"rank":2,"waku":6,"umaban":6,"name":"久田朔","kimarite":"捲"},{"rank":3,"waku":3,"umaban":3,"name":"小倉竜二","kimarite":""},{"rank":4,"waku":2,"umaban":2,"name":"杉森輝大","kimarite":""},{"rank":5,"waku":5,"umaban":5,"name":"上野優太","kimarite":""}],"paybacks":[{"type":"2車単","combination":"1-6","payout":740},{"type":"2車複","combination":"1-6","payout":380},{"type":"ワイド","combination":"1-3","payout":320},{"type":"ワイド","combination":"1-6","payout":210},{"type":"ワイド","combination":"3-6","payout":550},{"type":"3連単","combination":"1-6-3","payout":3170},{"type":"3連複","combination":"1-3-6","payout":1280}]},{"race_id":"202607135601","venue":"岸和田","race_no":1,"finishers":[{"rank":1,"waku":6,"umaban":7,"name":"山元大夢","kimarite":"逃"},{"rank":2,"waku":1,"umaban":1,"name":"杉山正和","kimarite":"ク"},{"rank":3,"waku":3,"umaban":3,"name":"羽石国臣","kimarite":""},{"rank":4,"waku":5,"umaban":5,"name":"池上孝之","kimarite":""},{"rank":5,"waku":2,"umaban":2,"name":"浜田翔平","kimarite":""}],"paybacks":[{"type":"2車単","combination":"7-1","payout":380},{"type":"2車複","combination":"1-7","payout":220},{"type":"ワイド","combination":"1-3","payout":420},{"type":"ワイド","combination":"1-7","payout":140},{"type":"ワイド","combination":"3-7","payout":250},{"type":"3連単","combination":"7-1-3","payout":1420},{"type":"3連複","combination":"1-3-7","payout":590}]},{"race_id":"202607135602","venue":"岸和田","race_no":2,"finishers":[{"rank":1,"waku":4,"umaban":4,"name":"大中拓磨","kimarite":"差"},{"rank":2,"waku":5,"umaban":5,"name":"大村涼兼","kimarite":"逃"},{"rank":3,"waku":6,"umaban":7,"name":"陶器一馬","kimarite":""},{"rank":4,"waku":1,"umaban":1,"name":"大崎龍一郎","kimarite":""},{"rank":5,"waku":6,"umaban":6,"name":"岡田大門","kimarite":""}],"paybacks":[{"type":"2車単","combination":"4-5","payout":1710},{"type":"2車複","combination":"4-5","payout":690},{"type":"ワイド","combination":"4-5","payout":180},{"type":"ワイド","combination":"4-7","payout":140},{"type":"ワイド","combination":"5-7","payout":310},{"type":"3連単","combination":"4-5-7","payout":6080},{"type":"3連複","combination":"4-5-7","payout":860}]},{"race_id":"202607135603","venue":"岸和田","race_no":3,"finishers":[{"rank":1,"waku":3,"umaban":3,"name":"柳沼鼓太朗","kimarite":"捲"},{"rank":2,"waku":6,"umaban":7,"name":"河合康晴","kimarite":"ク"},{"rank":3,"waku":5,"umaban":5,"name":"柴田健","kimarite":""},{"rank":4,"waku":6,"umaban":6,"name":"藤本龍也","kimarite":""},{"rank":5,"waku":2,"umaban":2,"name":"磯村蓮太","kimarite":""}],"paybacks":[{"type":"2車単","combination":"3-7","payout":230},{"type":"2車複","combination":"3-7","payout":170},{"type":"ワイド","combination":"3-5","payout":160},{"type":"ワイド","combination":"3-7","payout":120},{"type":"ワイド","combination":"5-7","payout":160},{"type":"3連単","combination":"3-7-5","payout":310},{"type":"3連複","combination":"3-5-7","payout":160}]},{"race_id":"202607135604","venue":"岸和田","race_no":4,"finishers":[{"rank":1,"waku":4,"umaban":4,"name":"高橋奏多","kimarite":"逃"},{"rank":2,"waku":3,"umaban":3,"name":"島田茂希","kimarite":"ク"},{"rank":3,"waku":6,"umaban":6,"name":"橋本祐司","kimarite":""},{"rank":4,"waku":1,"umaban":1,"name":"岡崎和久","kimarite":""},{"rank":5,"waku":6,"umaban":7,"name":"白崎芳典","kimarite":""}],"paybacks":[{"type":"2車単","combination":"4-3","payout":570},{"type":"2車複","combination":"3-4","payout":750},{"type":"ワイド","combination":"3-4","payout":180},{"type":"ワイド","combination":"3-6","payout":630},{"type":"ワイド","combination":"4-6","payout":450},{"type":"3連単","combination":"4-3-6","payout":1870},{"type":"3連複","combination":"3-4-6","payout":970}]},{"race_id":"202607135605","venue":"岸和田","race_no":5,"finishers":[{"rank":1,"waku":5,"umaban":5,"name":"竹野百香","kimarite":"逃"},{"rank":2,"waku":1,"umaban":1,"name":"畠山ひすい","kimarite":"ク"},{"rank":3,"waku":2,"umaban":2,"name":"高尾貴美歌","kimarite":""},{"rank":4,"waku":6,"umaban":6,"name":"高木佑真","kimarite":""},{"rank":5,"waku":6,"umaban":7,"name":"成海綾香","kimarite":""}],"paybacks":[{"type":"2車単","combination":"5-1","payout":270},{"type":"2車複","combination":"1-5","payout":160},{"type":"ワイド","combination":"1-2","payout":110},{"type":"ワイド","combination":"1-5","payout":100},{"type":"ワイド","combination":"2-5","payout":120},{"type":"3連単","combination":"5-1-2","payout":480},{"type":"3連複","combination":"1-2-5","payout":130}]},{"race_id":"202607135606","venue":"岸和田","race_no":6,"finishers":[{"rank":1,"waku":4,"umaban":4,"name":"松井優佳","kimarite":"差"},{"rank":2,"waku":1,"umaban":1,"name":"長澤彩","kimarite":"ク"},{"rank":3,"waku":6,"umaban":6,"name":"千葉捺美","kimarite":""},{"rank":4,"waku":6,"umaban":7,"name":"青木美保","kimarite":""},{"rank":5,"waku":2,"umaban":2,"name":"川田ひな","kimarite":""}],"paybacks":[{"type":"2車単","combination":"4-1","payout":680},{"type":"2車複","combination":"1-4","payout":480},{"type":"ワイド","combination":"1-4","payout":260},{"type":"ワイド","combination":"1-6","payout":660},{"type":"ワイド","combination":"4-6","payout":320},{"type":"3連単","combination":"4-1-6","payout":3750},{"type":"3連複","combination":"1-4-6","payout":1610}]},{"race_id":"202607135607","venue":"岸和田","race_no":7,"finishers":[{"rank":1,"waku":2,"umaban":2,"name":"鳥海創","kimarite":"逃"},{"rank":2,"waku":1,"umaban":1,"name":"泉谷直哉","kimarite":"差"},{"rank":3,"waku":5,"umaban":5,"name":"小林申太","kimarite":""},{"rank":4,"waku":3,"umaban":3,"name":"須賀和彦","kimarite":""},{"rank":5,"waku":4,"umaban":4,"name":"岡崎祥伍","kimarite":""}],"paybacks":[{"type":"2車単","combination":"2-1","payout":5480},{"type":"2車複","combination":"1-2","payout":3690},{"type":"ワイド","combination":"1-2","payout":450},{"type":"ワイド","combination":"1-5","payout":220},{"type":"ワイド","combination":"2-5","payout":1490},{"type":"3連単","combination":"2-1-5","payout":21490},{"type":"3連複","combination":"1-2-5","payout":3970}]},{"race_id":"202607135608","venue":"岸和田","race_no":8,"finishers":[{"rank":1,"waku":3,"umaban":3,"name":"藤田大輔","kimarite":"差"},{"rank":2,"waku":4,"umaban":4,"name":"吉田優斗","kimarite":"逃"},{"rank":3,"waku":6,"umaban":6,"name":"浅沼聖士","kimarite":""},{"rank":4,"waku":1,"umaban":1,"name":"長沼謙太","kimarite":""},{"rank":5,"waku":5,"umaban":5,"name":"瀧野勝太","kimarite":""}],"paybacks":[{"type":"2車単","combination":"3-4","payout":270},{"type":"2車複","combination":"3-4","payout":190},{"type":"ワイド","combination":"3-4","payout":140},{"type":"ワイド","combination":"3-6","payout":300},{"type":"ワイド","combination":"4-6","payout":330},{"type":"3連単","combination":"3-4-6","payout":1010},{"type":"3連複","combination":"3-4-6","payout":540}]},{"race_id":"202607135609","venue":"岸和田","race_no":9,"finishers":[{"rank":1,"waku":3,"umaban":3,"name":"土田栄二","kimarite":"逃"},{"rank":2,"waku":4,"umaban":4,"name":"山田義彦","kimarite":"ク"},{"rank":3,"waku":6,"umaban":6,"name":"関智晴","kimarite":""},{"rank":4,"waku":6,"umaban":7,"name":"藤岡徹也","kimarite":""},{"rank":5,"waku":1,"umaban":1,"name":"八嶋稔真","kimarite":""}],"paybacks":[{"type":"2車単","combination":"3-4","payout":410},{"type":"2車複","combination":"3-4","payout":140},{"type":"ワイド","combination":"3-4","payout":110},{"type":"ワイド","combination":"3-6","payout":470},{"type":"ワイド","combination":"4-6","payout":430},{"type":"3連単","combination":"3-4-6","payout":1000},{"type":"3連複","combination":"3-4-6","payout":460}]},{"race_id":"202607135610","venue":"岸和田","race_no":10,"finishers":[{"rank":1,"waku":3,"umaban":3,"name":"落合達彦","kimarite":"差"},{"rank":2,"waku":5,"umaban":5,"name":"金田涼馬","kimarite":"逃"},{"rank":3,"waku":2,"umaban":2,"name":"野崎翼","kimarite":""},{"rank":4,"waku":4,"umaban":4,"name":"新井剛央","kimarite":""},{"rank":5,"waku":6,"umaban":7,"name":"島野浩司","kimarite":""}],"paybacks":[{"type":"2車単","combination":"3-5","payout":290},{"type":"2車複","combination":"3-5","payout":120},{"type":"ワイド","combination":"2-3","payout":430},{"type":"ワイド","combination":"2-5","payout":510},{"type":"ワイド","combination":"3-5","payout":120},{"type":"3連単","combination":"3-5-2","payout":2440},{"type":"3連複","combination":"2-3-5","payout":750}]},{"race_id":"202607135611","venue":"岸和田","race_no":11,"finishers":[{"rank":1,"waku":6,"umaban":6,"name":"松澤敬輔","kimarite":"差"},{"rank":2,"waku":2,"umaban":2,"name":"菅野航基","kimarite":"逃"},{"rank":3,"waku":5,"umaban":5,"name":"福田拓也","kimarite":""},{"rank":4,"waku":1,"umaban":1,"name":"宮越孝治","kimarite":""},{"rank":5,"waku":3,"umaban":3,"name":"鈴木輝大","kimarite":""}],"paybacks":[{"type":"2車単","combination":"6-2","payout":4160},{"type":"2車複","combination":"2-6","payout":1480},{"type":"ワイド","combination":"2-5","payout":1370},{"type":"ワイド","combination":"2-6","payout":520},{"type":"ワイド","combination":"5-6","payout":1560},{"type":"3連単","combination":"6-2-5","payout":37410},{"type":"3連複","combination":"2-5-6","payout":8400}]},{"race_id":"202607136201","venue":"広島","race_no":1,"finishers":[{"rank":1,"waku":2,"umaban":2,"name":"吉岡詩織","kimarite":"捲"},{"rank":2,"waku":1,"umaban":1,"name":"當銘直美","kimarite":"差"},{"rank":3,"waku":5,"umaban":5,"name":"篠崎新純","kimarite":""},{"rank":4,"waku":3,"umaban":3,"name":"河内桜雪","kimarite":""},{"rank":5,"waku":6,"umaban":6,"name":"高本美穂","kimarite":""}],"paybacks":[{"type":"2車単","combination":"2-1","payout":300},{"type":"2車複","combination":"1-2","payout":180},{"type":"ワイド","combination":"1-2","payout":130},{"type":"ワイド","combination":"1-5","payout":640},{"type":"ワイド","combination":"2-5","payout":660},{"type":"3連単","combination":"2-1-5","payout":2990},{"type":"3連複","combination":"1-2-5","payout":1210}]},{"race_id":"202607136202","venue":"広島","race_no":2,"finishers":[{"rank":1,"waku":1,"umaban":1,"name":"児玉碧衣","kimarite":"逃"},{"rank":2,"waku":4,"umaban":4,"name":"比嘉真梨代","kimarite":"ク"},{"rank":3,"waku":6,"umaban":6,"name":"布居光","kimarite":""},{"rank":4,"waku":2,"umaban":2,"name":"奥井迪","kimarite":""},{"rank":5,"waku":3,"umaban":3,"name":"三森彩桜","kimarite":""}],"paybacks":[{"type":"2車単","combination":"1-4","payout":880},{"type":"2車複","combination":"1-4","payout":900},{"type":"ワイド","combination":"1-4","payout":310},{"type":"ワイド","combination":"1-6","payout":820},{"type":"ワイド","combination":"4-6","payout":4130},{"type":"3連単","combination":"1-4-6","payout":11890},{"type":"3連複","combination":"1-4-6","payout":6410}]},{"race_id":"202607136203","venue":"広島","race_no":3,"finishers":[{"rank":1,"waku":1,"umaban":1,"name":"富弥昭","kimarite":"差"},{"rank":2,"waku":4,"umaban":4,"name":"吉野太晟","kimarite":"逃"},{"rank":3,"waku":6,"umaban":6,"name":"郡英治","kimarite":""},{"rank":4,"waku":5,"umaban":5,"name":"高田真幸","kimarite":""},{"rank":5,"waku":2,"umaban":2,"name":"國武耕二","kimarite":""}],"paybacks":[{"type":"2車単","combination":"1-4","payout":180},{"type":"2車複","combination":"1-4","payout":130},{"type":"ワイド","combination":"1-4","payout":100},{"type":"ワイド","combination":"1-6","payout":120},{"type":"ワイド","combination":"4-6","payout":150},{"type":"3連単","combination":"1-4-6","payout":260},{"type":"3連複","combination":"1-4-6","payout":160}]},{"race_id":"202607137501","venue":"松山","race_no":1,"finishers":[{"rank":1,"waku":1,"umaban":1,"name":"上原直樹","kimarite":"差"},{"rank":2,"waku":4,"umaban":4,"name":"岡崎克政","kimarite":"逃"},{"rank":3,"waku":6,"umaban":7,"name":"住村実","kimarite":""},{"rank":4,"waku":2,"umaban":2,"name":"安部龍文","kimarite":""},{"rank":5,"waku":5,"umaban":5,"name":"小泉俊也","kimarite":""}],"paybacks":[{"type":"2車単","combination":"1-4","payout":520},{"type":"2車複","combination":"1-4","payout":260},{"type":"ワイド","combination":"1-4","payout":170},{"type":"ワイド","combination":"1-7","payout":250},{"type":"ワイド","combination":"4-7","payout":320},{"type":"3連単","combination":"1-4-7","payout":680},{"type":"3連複","combination":"1-4-7","payout":380}]},{"race_id":"202607137502","venue":"松山","race_no":2,"finishers":[{"rank":1,"waku":4,"umaban":4,"name":"森佑樹","kimarite":"捲"},{"rank":2,"waku":3,"umaban":3,"name":"織茂雄一郎","kimarite":"逃"},{"rank":3,"waku":5,"umaban":5,"name":"齊藤紳一朗","kimarite":""},{"rank":4,"waku":1,"umaban":1,"name":"長崎達也","kimarite":""},{"rank":5,"waku":6,"umaban":6,"name":"倉岡慎太郎","kimarite":""}],"paybacks":[{"type":"2車単","combination":"4-3","payout":1940},{"type":"2車複","combination":"3-4","payout":1470},{"type":"ワイド","combination":"3-4","payout":540},{"type":"ワイド","combination":"3-5","payout":280},{"type":"ワイド","combination":"4-5","payout":510},{"type":"3連単","combination":"4-3-5","payout":7680},{"type":"3連複","combination":"3-4-5","payout":1860}]},{"race_id":"202607137503","venue":"松山","race_no":3,"finishers":[{"rank":1,"waku":1,"umaban":1,"name":"徳吉正治","kimarite":"差"},{"rank":2,"waku":6,"umaban":6,"name":"駒壽直人","kimarite":"逃"},{"rank":3,"waku":6,"umaban":7,"name":"石井孝","kimarite":""},{"rank":4,"waku":2,"umaban":2,"name":"爲田学","kimarite":""},{"rank":5,"waku":3,"umaban":3,"name":"内田淳","kimarite":""}],"paybacks":[{"type":"2車単","combination":"1-6","payout":1300},{"type":"2車複","combination":"1-6","payout":630},{"type":"ワイド","combination":"1-6","payout":420},{"type":"ワイド","combination":"1-7","payout":1150},{"type":"ワイド","combination":"6-7","payout":1460},{"type":"3連単","combination":"1-6-7","payout":15580},{"type":"3連複","combination":"1-6-7","payout":5350}]},{"race_id":"202607137504","venue":"松山","race_no":4,"finishers":[{"rank":1,"waku":2,"umaban":2,"name":"伊藤梨里花","kimarite":"捲"},{"rank":2,"waku":3,"umaban":3,"name":"中嶋里美","kimarite":"ク"},{"rank":3,"waku":4,"umaban":4,"name":"東美月","kimarite":""},{"rank":4,"waku":6,"umaban":6,"name":"塩田日海","kimarite":""},{"rank":5,"waku":6,"umaban":7,"name":"枝光美奈","kimarite":""}],"paybacks":[{"type":"2車単","combination":"2-3","payout":480},{"type":"2車複","combination":"2-3","payout":380},{"type":"ワイド","combination":"2-3","payout":160},{"type":"ワイド","combination":"2-4","payout":130},{"type":"ワイド","combination":"3-4","payout":280},{"type":"3連単","combination":"2-3-4","payout":1030},{"type":"3連複","combination":"2-3-4","payout":350}]},{"race_id":"202607137505","venue":"松山","race_no":5,"finishers":[{"rank":1,"waku":1,"umaban":1,"name":"楢原由将","kimarite":"差"},{"rank":2,"waku":6,"umaban":7,"name":"高倉俊宏","kimarite":"差"},{"rank":3,"waku":4,"umaban":4,"name":"久保光司","kimarite":""},{"rank":4,"waku":6,"umaban":6,"name":"井上嵩","kimarite":""},{"rank":5,"waku":5,"umaban":5,"name":"平総一","kimarite":""}],"paybacks":[{"type":"2車単","combination":"1-7","payout":4060},{"type":"2車複","combination":"1-7","payout":330},{"type":"ワイド","combination":"1-4","payout":230},{"type":"ワイド","combination":"1-7","payout":150},{"type":"ワイド","combination":"4-7","payout":160},{"type":"3連単","combination":"1-7-4","payout":9300},{"type":"3連複","combination":"1-4-7","payout":240}]},{"race_id":"202607137506","venue":"松山","race_no":6,"finishers":[{"rank":1,"waku":6,"umaban":7,"name":"堀越翔己","kimarite":"捲"},{"rank":2,"waku":1,"umaban":1,"name":"松田優一","kimarite":"差"},{"rank":3,"waku":4,"umaban":4,"name":"黒滝大翔","kimarite":""},{"rank":4,"waku":6,"umaban":6,"name":"安谷屋将志","kimarite":""},{"rank":5,"waku":2,"umaban":2,"name":"八尋英輔","kimarite":""}],"paybacks":[{"type":"2車単","combination":"7-1","payout":8190},{"type":"2車複","combination":"1-7","payout":5270},{"type":"ワイド","combination":"1-4","payout":730},{"type":"ワイド","combination":"1-7","payout":1010},{"type":"ワイド","combination":"4-7","payout":1010},{"type":"3連単","combination":"7-1-4","payout":33650},{"type":"3連複","combination":"1-4-7","payout":5560}]},{"race_id":"202607137507","venue":"松山","race_no":7,"finishers":[{"rank":1,"waku":1,"umaban":1,"name":"篠原龍馬","kimarite":"逃"},{"rank":2,"waku":6,"umaban":6,"name":"越智展孝","kimarite":"ク"},{"rank":3,"waku":4,"umaban":4,"name":"名川豊","kimarite":""},{"rank":4,"waku":3,"umaban":3,"name":"大崎和也","kimarite":""},{"rank":5,"waku":5,"umaban":5,"name":"井上公利","kimarite":""}],"paybacks":[{"type":"2車単","combination":"1-6","payout":580},{"type":"2車複","combination":"1-6","payout":420},{"type":"ワイド","combination":"1-4","payout":170},{"type":"ワイド","combination":"1-6","payout":270},{"type":"ワイド","combination":"4-6","payout":400},{"type":"3連単","combination":"1-6-4","payout":1500},{"type":"3連複","combination":"1-4-6","payout":630}]},{"race_id":"202607137508","venue":"松山","race_no":8,"finishers":[{"rank":1,"waku":5,"umaban":5,"name":"比佐宝太","kimarite":"差"},{"rank":2,"waku":3,"umaban":3,"name":"齊藤竜也","kimarite":"ク"},{"rank":3,"waku":2,"umaban":2,"name":"中石昌芳","kimarite":""},{"rank":4,"waku":1,"umaban":1,"name":"寺沼将彦","kimarite":""},{"rank":5,"waku":6,"umaban":6,"name":"川越宏臣","kimarite":""}],"paybacks":[{"type":"2車単","combination":"5-3","payout":510},{"type":"2車複","combination":"3-5","payout":350},{"type":"ワイド","combination":"2-3","payout":300},{"type":"ワイド","combination":"2-5","payout":310},{"type":"ワイド","combination":"3-5","payout":180},{"type":"3連単","combination":"5-3-2","payout":1670},{"type":"3連複","combination":"2-3-5","payout":650}]},{"race_id":"202607137509","venue":"松山","race_no":9,"finishers":[{"rank":1,"waku":1,"umaban":1,"name":"渡邊諒馬","kimarite":"捲"},{"rank":2,"waku":4,"umaban":4,"name":"西原裕太郎","kimarite":"逃"},{"rank":3,"waku":2,"umaban":2,"name":"本馬鎌","kimarite":""},{"rank":4,"waku":5,"umaban":5,"name":"倉松涼","kimarite":""},{"rank":5,"waku":6,"umaban":6,"name":"赤松秀展","kimarite":""}],"paybacks":[{"type":"2車単","combination":"1-4","payout":700},{"type":"2車複","combination":"1-4","payout":440},{"type":"ワイド","combination":"1-2","payout":170},{"type":"ワイド","combination":"1-4","payout":210},{"type":"ワイド","combination":"2-4","payout":190},{"type":"3連単","combination":"1-4-2","payout":1860},{"type":"3連複","combination":"1-2-4","payout":440}]},{"race_id":"202607137510","venue":"松山","race_no":10,"finishers":[{"rank":1,"waku":6,"umaban":6,"name":"梅川風子","kimarite":"捲"},{"rank":2,"waku":4,"umaban":4,"name":"岡本二菜","kimarite":"逃"},{"rank":3,"waku":6,"umaban":7,"name":"西島叶子","kimarite":""},{"rank":4,"waku":1,"umaban":1,"name":"村田奈穂","kimarite":""},{"rank":5,"waku":3,"umaban":3,"name":"元砂七夕美","kimarite":""}],"paybacks":[{"type":"2車単","combination":"6-4","payout":340},{"type":"2車複","combination":"4-6","payout":210},{"type":"ワイド","combination":"4-6","payout":100},{"type":"ワイド","combination":"4-7","payout":340},{"type":"ワイド","combination":"6-7","payout":150},{"type":"3連単","combination":"6-4-7","payout":780},{"type":"3連複","combination":"4-6-7","payout":300}]},{"race_id":"202607137511","venue":"松山","race_no":11,"finishers":[{"rank":1,"waku":2,"umaban":2,"name":"小玉拓真","kimarite":"差"},{"rank":2,"waku":6,"umaban":7,"name":"諸隈健太郎","kimarite":"逃"},{"rank":3,"waku":3,"umaban":3,"name":"中村健志","kimarite":""},{"rank":4,"waku":6,"umaban":6,"name":"高橋義秋","kimarite":""},{"rank":5,"waku":1,"umaban":1,"name":"日野博幸","kimarite":""}],"paybacks":[{"type":"2車単","combination":"2-7","payout":980},{"type":"2車複","combination":"2-7","payout":480},{"type":"ワイド","combination":"2-3","payout":160},{"type":"ワイド","combination":"2-7","payout":160},{"type":"ワイド","combination":"3-7","payout":240},{"type":"3連単","combination":"2-7-3","payout":3710},{"type":"3連複","combination":"2-3-7","payout":840}]},{"race_id":"202607138501","venue":"佐世保","race_no":1,"finishers":[{"rank":1,"waku":5,"umaban":5,"name":"小野裕次","kimarite":"差"},{"rank":2,"waku":1,"umaban":1,"name":"安東宏高","kimarite":"差"},{"rank":3,"waku":3,"umaban":3,"name":"照井力斗","kimarite":""},{"rank":4,"waku":2,"umaban":2,"name":"阿部充宏","kimarite":""},{"rank":5,"waku":6,"umaban":7,"name":"高比良豪","kimarite":""}],"paybacks":[{"type":"2車単","combination":"5-1","payout":2680},{"type":"2車複","combination":"1-5","payout":1780},{"type":"ワイド","combination":"1-3","payout":230},{"type":"ワイド","combination":"1-5","payout":220},{"type":"ワイド","combination":"3-5","payout":120},{"type":"3連単","combination":"5-1-3","payout":4990},{"type":"3連複","combination":"1-3-5","payout":490}]},{"race_id":"202607138502","venue":"佐世保","race_no":2,"finishers":[{"rank":1,"waku":4,"umaban":4,"name":"滝本泰行","kimarite":"差"},{"rank":2,"waku":1,"umaban":1,"name":"藤原悠斗","kimarite":"ク"},{"rank":3,"waku":5,"umaban":5,"name":"松本卓也","kimarite":""},{"rank":4,"waku":2,"umaban":2,"name":"鮒田博文","kimarite":""},{"rank":5,"waku":6,"umaban":6,"name":"森川剛","kimarite":""}],"paybacks":[{"type":"2車単","combination":"4-1","payout":720},{"type":"2車複","combination":"1-4","payout":580},{"type":"ワイド","combination":"1-4","payout":130},{"type":"ワイド","combination":"1-5","payout":150},{"type":"ワイド","combination":"4-5","payout":100},{"type":"3連単","combination":"4-1-5","payout":1140},{"type":"3連複","combination":"1-4-5","payout":140}]},{"race_id":"202607138503","venue":"佐世保","race_no":3,"finishers":[{"rank":1,"waku":4,"umaban":4,"name":"中村翔平","kimarite":"差"},{"rank":2,"waku":1,"umaban":1,"name":"小原亮哉","kimarite":"ク"},{"rank":3,"waku":5,"umaban":5,"name":"佐藤明","kimarite":""},{"rank":4,"waku":2,"umaban":2,"name":"日当泰之","kimarite":""},{"rank":5,"waku":3,"umaban":3,"name":"小川達也","kimarite":""}],"paybacks":[{"type":"2車単","combination":"4-1","payout":450},{"type":"2車複","combination":"1-4","payout":220},{"type":"ワイド","combination":"1-4","payout":180},{"type":"ワイド","combination":"1-5","payout":740},{"type":"ワイド","combination":"4-5","payout":390},{"type":"3連単","combination":"4-1-5","payout":3610},{"type":"3連複","combination":"1-4-5","payout":1420}]},{"race_id":"202607138504","venue":"佐世保","race_no":4,"finishers":[{"rank":1,"waku":5,"umaban":5,"name":"藤井優希","kimarite":"逃"},{"rank":2,"waku":2,"umaban":2,"name":"宇根秀俊","kimarite":"ク"},{"rank":3,"waku":3,"umaban":3,"name":"三槻智清","kimarite":""},{"rank":4,"waku":1,"umaban":1,"name":"大塚英伸","kimarite":""},{"rank":5,"waku":6,"umaban":7,"name":"金子兼久","kimarite":""}],"paybacks":[{"type":"2車単","combination":"5-2","payout":250},{"type":"2車複","combination":"2-5","payout":160},{"type":"ワイド","combination":"2-3","payout":300},{"type":"ワイド","combination":"2-5","payout":160},{"type":"ワイド","combination":"3-5","payout":270},{"type":"3連単","combination":"5-2-3","payout":590},{"type":"3連複","combination":"2-3-5","payout":420}]},{"race_id":"202607138505","venue":"佐世保","race_no":5,"finishers":[{"rank":1,"waku":2,"umaban":2,"name":"松本定","kimarite":"差"},{"rank":2,"waku":5,"umaban":5,"name":"梅澤忠秀","kimarite":"捲"},{"rank":3,"waku":3,"umaban":3,"name":"山本勝利","kimarite":""},{"rank":4,"waku":4,"umaban":4,"name":"大西祐","kimarite":""}],"paybacks":[{"type":"2車単","combination":"2-5","payout":1470},{"type":"2車複","combination":"2-5","payout":1460},{"type":"ワイド","combination":"2-3","payout":160},{"type":"ワイド","combination":"2-5","payout":490},{"type":"ワイド","combination":"3-5","payout":710},{"type":"3連単","combination":"2-5-3","payout":8120},{"type":"3連複","combination":"2-3-5","payout":1600}]},{"race_id":"202607138506","venue":"佐世保","race_no":6,"finishers":[{"rank":1,"waku":5,"umaban":5,"name":"鈴木美教","kimarite":"捲"},{"rank":2,"waku":6,"umaban":7,"name":"那須萌美","kimarite":"捲"},{"rank":3,"waku":2,"umaban":2,"name":"細田愛未","kimarite":""},{"rank":4,"waku":4,"umaban":4,"name":"島田優里","kimarite":""},{"rank":5,"waku":3,"umaban":3,"name":"高崎千賀","kimarite":""}],"paybacks":[{"type":"2車単","combination":"5-7","payout":520},{"type":"2車複","combination":"5-7","payout":230},{"type":"ワイド","combination":"2-5","payout":120},{"type":"ワイド","combination":"2-7","payout":110},{"type":"ワイド","combination":"5-7","payout":100},{"type":"3連単","combination":"5-7-2","payout":730},{"type":"3連複","combination":"2-5-7","payout":140}]},{"race_id":"202607138507","venue":"佐世保","race_no":7,"finishers":[{"rank":1,"waku":1,"umaban":1,"name":"小林莉子","kimarite":"捲"},{"rank":2,"waku":3,"umaban":3,"name":"太田美穂","kimarite":"逃"},{"rank":3,"waku":6,"umaban":6,"name":"磯村光舞","kimarite":""},{"rank":4,"waku":4,"umaban":4,"name":"青木美優","kimarite":""},{"rank":5,"waku":5,"umaban":5,"name":"田中千尋","kimarite":""}],"paybacks":[{"type":"2車単","combination":"1-3","payout":200},{"type":"2車複","combination":"1-3","payout":180},{"type":"ワイド","combination":"1-3","payout":100},{"type":"ワイド","combination":"1-6","payout":130},{"type":"ワイド","combination":"3-6","payout":170},{"type":"3連単","combination":"1-3-6","payout":300},{"type":"3連複","combination":"1-3-6","payout":120}]},{"race_id":"202607138508","venue":"佐世保","race_no":8,"finishers":[{"rank":1,"waku":4,"umaban":4,"name":"野口裕史","kimarite":"逃"},{"rank":2,"waku":5,"umaban":5,"name":"横関裕樹","kimarite":"差"},{"rank":3,"waku":3,"umaban":3,"name":"田中晴基","kimarite":""},{"rank":4,"waku":6,"umaban":7,"name":"竹内雄作","kimarite":""},{"rank":5,"waku":6,"umaban":6,"name":"小橋秀幸","kimarite":""}],"paybacks":[{"type":"2車単","combination":"4-5","payout":1270},{"type":"2車複","combination":"4-5","payout":790},{"type":"ワイド","combination":"3-4","payout":150},{"type":"ワイド","combination":"3-5","payout":160},{"type":"ワイド","combination":"4-5","payout":200},{"type":"3連単","combination":"4-5-3","payout":2060},{"type":"3連複","combination":"3-4-5","payout":270}]},{"race_id":"202607138509","venue":"佐世保","race_no":9,"finishers":[{"rank":1,"waku":2,"umaban":2,"name":"古川尚耶","kimarite":"差"},{"rank":2,"waku":5,"umaban":5,"name":"河合佑弥","kimarite":"逃"},{"rank":3,"waku":1,"umaban":1,"name":"原口昌平","kimarite":""},{"rank":4,"waku":4,"umaban":4,"name":"山口貴嗣","kimarite":""},{"rank":5,"waku":3,"umaban":3,"name":"黒田淳","kimarite":""}],"paybacks":[{"type":"2車単","combination":"2-5","payout":3850},{"type":"2車複","combination":"2-5","payout":750},{"type":"ワイド","combination":"1-2","payout":600},{"type":"ワイド","combination":"1-5","payout":340},{"type":"ワイド","combination":"2-5","payout":420},{"type":"3連単","combination":"2-5-1","payout":14700},{"type":"3連複","combination":"1-2-5","payout":1080}]},{"race_id":"202607138510","venue":"佐世保","race_no":10,"finishers":[{"rank":1,"waku":2,"umaban":2,"name":"木村佑来","kimarite":"逃"},{"rank":2,"waku":6,"umaban":6,"name":"長井妙樹","kimarite":"差"},{"rank":3,"waku":4,"umaban":4,"name":"門田凌","kimarite":""},{"rank":4,"waku":6,"umaban":7,"name":"佐伯翔","kimarite":""},{"rank":5,"waku":5,"umaban":5,"name":"石塚慶一郎","kimarite":""}],"paybacks":[{"type":"2車単","combination":"2-6","payout":9020},{"type":"2車複","combination":"2-6","payout":5180},{"type":"ワイド","combination":"2-4","payout":1270},{"type":"ワイド","combination":"2-6","payout":1100},{"type":"ワイド","combination":"4-6","payout":2350},{"type":"3連単","combination":"2-6-4","payout":87790},{"type":"3連複","combination":"2-4-6","payout":15170}]},{"race_id":"202607138511","venue":"佐世保","race_no":11,"finishers":[{"rank":1,"waku":6,"umaban":7,"name":"上田尭弥","kimarite":"捲"},{"rank":2,"waku":6,"umaban":6,"name":"酒井拳蔵","kimarite":"捲"},{"rank":3,"waku":3,"umaban":3,"name":"鈴木伸之","kimarite":""},{"rank":4,"waku":1,"umaban":1,"name":"稲吉悠大","kimarite":""},{"rank":5,"waku":5,"umaban":5,"name":"出澤拓也","kimarite":""}],"paybacks":[{"type":"2車単","combination":"7-6","payout":7770},{"type":"2車複","combination":"6-7","payout":4390},{"type":"ワイド","combination":"3-6","payout":890},{"type":"ワイド","combination":"3-7","payout":640},{"type":"ワイド","combination":"6-7","payout":1060},{"type":"3連単","combination":"7-6-3","payout":33500},{"type":"3連複","combination":"3-6-7","payout":3900}]},{"race_id":"202607138512","venue":"佐世保","race_no":12,"finishers":[{"rank":1,"waku":4,"umaban":4,"name":"山形一気","kimarite":"捲"},{"rank":2,"waku":6,"umaban":7,"name":"谷口遼平","kimarite":"差"},{"rank":3,"waku":2,"umaban":2,"name":"笠松信幸","kimarite":""},{"rank":4,"waku":1,"umaban":1,"name":"須永優太","kimarite":""},{"rank":5,"waku":5,"umaban":5,"name":"松坂洋平","kimarite":""}],"paybacks":[{"type":"2車単","combination":"4-7","payout":4970},{"type":"2車複","combination":"4-7","payout":1820},{"type":"ワイド","combination":"2-4","payout":470},{"type":"ワイド","combination":"2-7","payout":290},{"type":"ワイド","combination":"4-7","payout":500},{"type":"3連単","combination":"4-7-2","payout":12340},{"type":"3連複","combination":"2-4-7","payout":810}]},{"race_id":"202607138701","venue":"熊本","race_no":1,"finishers":[{"rank":1,"waku":6,"umaban":7,"name":"田中衛太","kimarite":"逃"},{"rank":2,"waku":2,"umaban":2,"name":"照屋将貴","kimarite":"ク"},{"rank":3,"waku":4,"umaban":4,"name":"水野悟志","kimarite":""},{"rank":4,"waku":3,"umaban":3,"name":"井坂泰誓","kimarite":""},{"rank":5,"waku":5,"umaban":5,"name":"石貞有基","kimarite":""}],"paybacks":[{"type":"2車単","combination":"7-2","payout":170},{"type":"2車複","combination":"2-7","payout":140},{"type":"ワイド","combination":"2-4","payout":400},{"type":"ワイド","combination":"2-7","payout":120},{"type":"ワイド","combination":"4-7","payout":340},{"type":"3連単","combination":"7-2-4","payout":420},{"type":"3連複","combination":"2-4-7","payout":350}]},{"race_id":"202607138702","venue":"熊本","race_no":2,"finishers":[{"rank":1,"waku":1,"umaban":1,"name":"松本悠平","kimarite":"逃"},{"rank":2,"waku":2,"umaban":2,"name":"大越啓介","kimarite":"差"},{"rank":3,"waku":4,"umaban":4,"name":"中秀平","kimarite":""},{"rank":4,"waku":6,"umaban":7,"name":"青木亮太","kimarite":""},{"rank":5,"waku":6,"umaban":6,"name":"岡田浩太","kimarite":""}],"paybacks":[{"type":"2車単","combination":"1-2","payout":780},{"type":"2車複","combination":"1-2","payout":540},{"type":"ワイド","combination":"1-2","payout":230},{"type":"ワイド","combination":"1-4","payout":350},{"type":"ワイド","combination":"2-4","payout":110},{"type":"3連単","combination":"1-2-4","payout":1850},{"type":"3連複","combination":"1-2-4","payout":470}]},{"race_id":"202607138703","venue":"熊本","race_no":3,"finishers":[{"rank":1,"waku":4,"umaban":4,"name":"菱沼元樹","kimarite":"逃"},{"rank":2,"waku":3,"umaban":3,"name":"渡邊政幸","kimarite":"ク"},{"rank":3,"waku":6,"umaban":7,"name":"松木一将","kimarite":""},{"rank":4,"waku":1,"umaban":1,"name":"小塚潤","kimarite":""},{"rank":5,"waku":2,"umaban":2,"name":"楠本政明","kimarite":""}],"paybacks":[{"type":"2車単","combination":"4-3","payout":300},{"type":"2車複","combination":"3-4","payout":180},{"type":"ワイド","combination":"3-4","payout":130},{"type":"ワイド","combination":"3-7","payout":370},{"type":"ワイド","combination":"4-7","payout":510},{"type":"3連単","combination":"4-3-7","payout":2910},{"type":"3連複","combination":"3-4-7","payout":830}]},{"race_id":"202607138704","venue":"熊本","race_no":4,"finishers":[{"rank":1,"waku":1,"umaban":1,"name":"飯田怜治","kimarite":"逃"},{"rank":2,"waku":4,"umaban":4,"name":"伊狩知人","kimarite":"差"},{"rank":3,"waku":6,"umaban":7,"name":"塩川真一郎","kimarite":""},{"rank":4,"waku":5,"umaban":5,"name":"喜納隆志","kimarite":""},{"rank":5,"waku":3,"umaban":3,"name":"古川大輔","kimarite":""}],"paybacks":[{"type":"2車単","combination":"1-4","payout":3400},{"type":"2車複","combination":"1-4","payout":3570},{"type":"ワイド","combination":"1-4","payout":560},{"type":"ワイド","combination":"1-7","payout":300},{"type":"ワイド","combination":"4-7","payout":2880},{"type":"3連単","combination":"1-4-7","payout":28240},{"type":"3連複","combination":"1-4-7","payout":6090}]},{"race_id":"202607138705","venue":"熊本","race_no":5,"finishers":[{"rank":1,"waku":5,"umaban":5,"name":"邊見祐太","kimarite":"捲"},{"rank":2,"waku":6,"umaban":6,"name":"吉成晃一","kimarite":"差"},{"rank":3,"waku":6,"umaban":7,"name":"富澤洋祐","kimarite":""},{"rank":4,"waku":1,"umaban":1,"name":"山村慮太","kimarite":""},{"rank":5,"waku":3,"umaban":3,"name":"佐藤和典","kimarite":""}],"paybacks":[{"type":"2車単","combination":"5-6","payout":5500},{"type":"2車複","combination":"5-6","payout":4550},{"type":"ワイド","combination":"5-6","payout":860},{"type":"ワイド","combination":"5-7","payout":600},{"type":"ワイド","combination":"6-7","payout":3840},{"type":"3連単","combination":"5-6-7","payout":54380},{"type":"3連複","combination":"5-6-7","payout":25120}]},{"race_id":"202607138706","venue":"熊本","race_no":6,"finishers":[{"rank":1,"waku":6,"umaban":6,"name":"牧田賢也","kimarite":"差"},{"rank":2,"waku":4,"umaban":4,"name":"中井大介","kimarite":"差"},{"rank":3,"waku":1,"umaban":1,"name":"佐藤魁皇","kimarite":""},{"rank":4,"waku":2,"umaban":2,"name":"前川裕希","kimarite":""},{"rank":5,"waku":5,"umaban":5,"name":"湯浅弘光","kimarite":""}],"paybacks":[{"type":"2車単","combination":"6-4","payout":5060},{"type":"2車複","combination":"4-6","payout":2800},{"type":"ワイド","combination":"1-4","payout":110},{"type":"ワイド","combination":"1-6","payout":480},{"type":"ワイド","combination":"4-6","payout":480},{"type":"3連単","combination":"6-4-1","payout":9880},{"type":"3連複","combination":"1-4-6","payout":1090}]},{"race_id":"202607138707","venue":"熊本","race_no":7,"finishers":[{"rank":1,"waku":3,"umaban":3,"name":"南部亮太","kimarite":"差"},{"rank":2,"waku":6,"umaban":7,"name":"沢田桂太郎","kimarite":"逃"},{"rank":3,"waku":1,"umaban":1,"name":"関根崇人","kimarite":""},{"rank":4,"waku":4,"umaban":4,"name":"廣川貞治","kimarite":""},{"rank":5,"waku":6,"umaban":6,"name":"伊藤司","kimarite":""}],"paybacks":[{"type":"2車単","combination":"3-7","payout":640},{"type":"2車複","combination":"3-7","payout":110},{"type":"ワイド","combination":"1-3","payout":290},{"type":"ワイド","combination":"1-7","payout":220},{"type":"ワイド","combination":"3-7","payout":100},{"type":"3連単","combination":"3-7-1","payout":1690},{"type":"3連複","combination":"1-3-7","payout":300}]}]}